bktest/__init__.py
bktest/__main__.py
bktest/__version__.py
bktest/account.py
bktest/backtest.py
bktest/cli.py
bktest/constants.py
bktest/fee.py
bktest/holding.py
bktest/iterator.py
bktest/order.py
bktest/price_provider.py
bktest/utils.py
bktest/data/__init__.py
bktest/data/holidays.py
bktest/data/source/__init__.py
bktest/data/source/base.py
bktest/data/source/coinmarketcap.py
bktest/data/source/dataframe.py
bktest/data/source/delegate.py
bktest/data/source/factset.py
bktest/data/source/yahoo.py
bktest/export/__init__.py
bktest/export/base.py
bktest/export/console.py
bktest/export/dump.py
bktest/export/model.py
bktest/export/pdf.py
bktest/export/quants.py
bktest/export/specific_return.py
bktest/template/__init__.py
bktest/template/models.py
bktest/template/pdf.py
bktest/template/sketch.py
bktest/template/template.py
tests/__init__.py
tests/test_account.py
tests/test_data_source.py
tests/test_fee.py
tests/test_holdings.py
tests/test_iterator.py
tests/test_order.py
tests/test_utils.py
bktest-2.1.0.dist-info/METADATA
bktest-2.1.0.dist-info/WHEEL
bktest-2.1.0.dist-info/entry_points.txt
bktest-2.1.0.dist-info/top_level.txt
bktest-2.1.0.dist-info/RECORD
