Metadata-Version: 2.1
Name: bktest
Version: 2.1.0
Summary: bktest - A simple backtester by CrunchDAO
Home-page: https://github.com/crunchdao/backtest
Author: Enzo CACERES
Author-email: enzo.caceres@crunchdao.com
Keywords: package development template
Classifier: Intended Audience :: Developers
Classifier: Programming Language :: Python :: 3.7
Requires-Python: >=3
Requires-Dist: click <8.1.2,>=8.0
Requires-Dist: pandas <2.0.0,>=1.5
Requires-Dist: python-dateutil <2.8.3,>=2.8.2
Requires-Dist: tqdm <4.65.0,>=4.48.0
Requires-Dist: numpy <1.25.0,>=1.23.0
Requires-Dist: py-expression-eval <0.3.14,>=0.3.9
Requires-Dist: pyarrow <12.0,>=11.0
Requires-Dist: quantstats ==0.0.62
Requires-Dist: pytest <7.3.0,>=7.1.0
Requires-Dist: yfinance <0.2.27,>=0.2.24
Requires-Dist: python-dotenv <1.0.0,>=0.20
Requires-Dist: colorama <0.4.6,>=0.4.4
Requires-Dist: ipython ==8.15.0
Requires-Dist: seaborn <0.13.0,>=0.12.0
Requires-Dist: python-slugify
Requires-Dist: cached-property
Requires-Dist: fpdf2 ==2.7.4
Requires-Dist: contexttimer
Requires-Dist: watchdog
Requires-Dist: fastparquet
Requires-Dist: readwrite
Requires-Dist: holidays
